<annotation>
	<folder></folder>
	<filename>IMG20230921215708_jpg.rf.aa9a84cd405a229977de2bd0b8681d96.jpg</filename>
	<path>IMG20230921215708_jpg.rf.aa9a84cd405a229977de2bd0b8681d96.jpg</path>
	<source>
		<database>roboflow.com</database>
	</source>
	<size>
		<width>640</width>
		<height>640</height>
		<depth>3</depth>
	</size>
	<segmented>0</segmented>
	<object>
		<name>box</name>
		<pose>Unspecified</pose>
		<truncated>0</truncated>
		<difficult>0</difficult>
		<occluded>0</occluded>
		<bndbox>
			<xmin>126</xmin>
			<xmax>433</xmax>
			<ymin>215</ymin>
			<ymax>432</ymax>
		</bndbox>
		<polygon>
			<x1>401.384083</x1>
			<y1>214.071511</y1>
			<x2>124.567474</x2>
			<y2>243.598616</y2>
			<x3>144.867359</x3>
			<y3>430.911188</y3>
			<x4>431.83391</x4>
			<y4>395.847751</y4>
			<x5>401.384083</x5>
			<y5>214.071511</y5>
		</polygon>
	</object>
</annotation>
