<annotation>
	<folder></folder>
	<filename>IMG20230915161439_jpg.rf.c1186965cb079bf4c2ecb56cb3211478.jpg</filename>
	<path>IMG20230915161439_jpg.rf.c1186965cb079bf4c2ecb56cb3211478.jpg</path>
	<source>
		<database>roboflow.com</database>
	</source>
	<size>
		<width>640</width>
		<height>640</height>
		<depth>3</depth>
	</size>
	<segmented>0</segmented>
	<object>
		<name>box</name>
		<pose>Unspecified</pose>
		<truncated>0</truncated>
		<difficult>0</difficult>
		<occluded>0</occluded>
		<bndbox>
			<xmin>126</xmin>
			<xmax>550</xmax>
			<ymin>269</ymin>
			<ymax>422</ymax>
		</bndbox>
		<polygon>
			<x1>549.019608</x1>
			<y1>278.662053</y1>
			<x2>129.181084</x2>
			<y2>267.589389</y2>
			<x3>125.490196</x3>
			<y3>397.693195</y3>
			<x4>541.637832</x4>
			<y4>420.761246</y4>
			<x5>549.019608</x5>
			<y5>278.662053</y5>
		</polygon>
	</object>
</annotation>
